youtube_channel_scraper/__init__.py
youtube_channel_scraper/__main__.py
youtube_channel_scraper/scraper.py
youtube_channel_scraper/utils.py
youtube_channel_scraper-0.1.3.dist-info/entry_points.txt
youtube_channel_scraper-0.1.3.dist-info/WHEEL
youtube_channel_scraper-0.1.3.dist-info/METADATA
youtube_channel_scraper-0.1.3.dist-info/RECORD
