Metadata-Version: 2.1
Name: youtube-channel-scraper
Version: 0.1.3
Summary: Scrape videos from YouTube channels.
Home-page: https://github.com/hajkr/youtube-channel-scraper
License: MIT
Author: Tadej Hribar
Author-email: tadej.996@gmail.com
Requires-Python: >=2.7
Classifier: License :: OSI Approved :: MIT License
Classifier: Programming Language :: Python :: 2
Classifier: Programming Language :: Python :: 2.7
Classifier: Programming Language :: Python :: 3
Classifier: Programming Language :: Python :: 3.4
Classifier: Programming Language :: Python :: 3.5
Classifier: Programming Language :: Python :: 3.6
Classifier: Programming Language :: Python :: 3.7
Classifier: Programming Language :: Python :: 3.8
Classifier: Programming Language :: Python :: 3.9
Requires-Dist: selenium (>=3.141.0,<4.0.0)
Project-URL: Repository, https://github.com/hajkr/youtube-channel-scraper
